lensai_profiler/__init__.py
lensai_profiler/metrics.py
lensai_profiler/sketches.py
lensai_profiler/utils.py
tests/__init__.py
tests/test_metrics.py
tests/test_sketches.py
lensai_profiler-1.2.2.dist-info/LICENSE
lensai_profiler-1.2.2.dist-info/METADATA
lensai_profiler-1.2.2.dist-info/WHEEL
lensai_profiler-1.2.2.dist-info/top_level.txt
lensai_profiler-1.2.2.dist-info/RECORD
