Metadata-Version: 2.1
Name: lensai_profiler
Version: 1.2.2
Summary: LensAI: A Python Library for Image and Model Profiling with Probabilistic Data Structures using TensorFlow
Home-page: https://github.com/lens-ai/lensai_profiler
Author: Venkata Pydipalli
Author-email: vsnm.tej@gmail.com
Classifier: Programming Language :: Python :: 3
Classifier: License :: OSI Approved :: MIT License
Classifier: Operating System :: OS Independent
Requires-Python: >=3.6
License-File: LICENSE
Requires-Dist: numpy==1.24.3
Requires-Dist: datasketches
Requires-Dist: requests==2.32.3
Provides-Extra: tensorflow
Requires-Dist: tensorflow>=2.0.0; extra == "tensorflow"
Provides-Extra: torch
Requires-Dist: torch>=1.0.0; extra == "torch"
